{
  "#chat_message": {
     "misc":
     {
       "text_horiz_alignment": "left",
       "text_vert_alignment": "top",
       "padding": "2, 2"
     }
   },
  "#chat_message_system": {
    "colours":
    {
      "normal_text": "#999999"
    },
    "font":
    {
      "size": 14
    },
    "misc":
    {
      "text_horiz_alignment": "left",
      "text_vert_alignment": "top",
      "text_horiz_alignment_padding": "2",
      "text_vert_alignment_padding": "2"
    }
  },
  "#chat_message_chat": {
    "colours":
    {
      "normal_text": "#ffffff"
    },
    "font":
    {
      "size": 14
    },
    "misc":
    {
      "text_horiz_alignment": "left",
      "text_vert_alignment": "top",
      "text_horiz_alignment_padding": "2",
      "text_vert_alignment_padding": "2"
    }
  },
  "#chat_message_combat": {
    "colours":
    {
      "normal_text": "#ff6666"
    },
    "font":
    {
      "size": 14
    },
    "misc":
    {
      "text_horiz_alignment": "left",
      "text_vert_alignment": "top",
      "text_horiz_alignment_padding": "2",
      "text_vert_alignment_padding": "2"
    }
  },
  "#chat_message_admin": {
    "colours":
    {
      "normal_text": "#00ffff"
    },
    "font":
    {
      "size": 14
    },
    "misc":
    {
      "text_horiz_alignment": "left",
      "text_vert_alignment": "top",
      "text_horiz_alignment_padding": "2",
      "text_vert_alignment_padding": "2"
    }
  },
  "#chat_message_debug": {
    "colours":
    {
      "normal_text": "#c800ff"
    },
    "font":
    {
      "size": 14
    },
    "misc":
    {
      "text_horiz_alignment": "left",
      "text_vert_alignment": "top",
      "text_horiz_alignment_padding": "2",
      "text_vert_alignment_padding": "2"
    }
  },
  "#chat_message_whisper": {
    "colours":
    {
      "normal_text": "#b266ff"
    },
    "font":
    {
      "size": 14
    },
    "misc":
    {
      "text_horiz_alignment": "left",
      "text_vert_alignment": "top",
      "text_horiz_alignment_padding": "2",
      "text_vert_alignment_padding": "2"
    }
  },
  "#error_label": {
    "colours":
    {
      "normal_bg":"#8B0000",
      "dark_bg":"#8B0000",
      "normal_text": "#FFFFFF"
    },
    "font":
    {
      "size": 14
    },
    "misc":
    {
      "text_horiz_alignment": "center",
      "text_vert_alignment": "top",
      "text_horiz_alignment_padding": "2",
      "text_vert_alignment_padding": "2"
    }
  },
  "#enemy_title_label": {
    "colours":
    {
      "normal_border": "#00000000",
      "dark_bg": "#00000000"
    },
    "misc":
    {
      "text_horiz_alignment": "center",
      "text_vert_alignment": "top"
    }
  },
  "#battle_hp_label": {
    "colours":
    {
      "normal_border": "#00000000",
      "dark_bg": "#00000000"
    },
    "misc":
    {
      "text_horiz_alignment": "center",
      "text_vert_alignment": "top"
    }
  },
  "#login_banner": {
    "colours":
    {
      "normal_border": "#00000000",
      "dark_bg": "#00000000",
      "normal_text": "#bcbf0a"
    },
    "misc":
    {
      "text_horiz_alignment": "center",
      "text_vert_alignment": "center"
    }
  }
}

